{
  "status": "success",
  "total": 15,
  "data": [
    {
      "nama_wilayah": "Kapuas",
      "kode_wilayah": "61.03.01",
      "level_wilayah": "kecamatan",
      "kode_kabupaten_kota": "61.03",
      "kode_provinsi": "61"
    },
    {
      "nama_wilayah": "Mukok",
      "kode_wilayah": "61.03.02",
      "level_wilayah": "kecamatan",
      "kode_kabupaten_kota": "61.03",
      "kode_provinsi": "61"
    },
    {
      "nama_wilayah": "Noyan",
      "kode_wilayah": "61.03.03",
      "level_wilayah": "kecamatan",
      "kode_kabupaten_kota": "61.03",
      "kode_provinsi": "61"
    },
    {
      "nama_wilayah": "Jangkang",
      "kode_wilayah": "61.03.04",
      "level_wilayah": "kecamatan",
      "kode_kabupaten_kota": "61.03",
      "kode_provinsi": "61"
    },
    {
      "nama_wilayah": "Bonti",
      "kode_wilayah": "61.03.05",
      "level_wilayah": "kecamatan",
      "kode_kabupaten_kota": "61.03",
      "kode_provinsi": "61"
    },
    {
      "nama_wilayah": "Beduai",
      "kode_wilayah": "61.03.06",
      "level_wilayah": "kecamatan",
      "kode_kabupaten_kota": "61.03",
      "kode_provinsi": "61"
    },
    {
      "nama_wilayah": "Sekayam",
      "kode_wilayah": "61.03.07",
      "level_wilayah": "kecamatan",
      "kode_kabupaten_kota": "61.03",
      "kode_provinsi": "61"
    },
    {
      "nama_wilayah": "Kembayan",
      "kode_wilayah": "61.03.08",
      "level_wilayah": "kecamatan",
      "kode_kabupaten_kota": "61.03",
      "kode_provinsi": "61"
    },
    {
      "nama_wilayah": "Parindu",
      "kode_wilayah": "61.03.09",
      "level_wilayah": "kecamatan",
      "kode_kabupaten_kota": "61.03",
      "kode_provinsi": "61"
    },
    {
      "nama_wilayah": "Tayan Hulu",
      "kode_wilayah": "61.03.10",
      "level_wilayah": "kecamatan",
      "kode_kabupaten_kota": "61.03",
      "kode_provinsi": "61"
    },
    {
      "nama_wilayah": "Tayan Hilir",
      "kode_wilayah": "61.03.11",
      "level_wilayah": "kecamatan",
      "kode_kabupaten_kota": "61.03",
      "kode_provinsi": "61"
    },
    {
      "nama_wilayah": "Balai",
      "kode_wilayah": "61.03.12",
      "level_wilayah": "kecamatan",
      "kode_kabupaten_kota": "61.03",
      "kode_provinsi": "61"
    },
    {
      "nama_wilayah": "Toba",
      "kode_wilayah": "61.03.13",
      "level_wilayah": "kecamatan",
      "kode_kabupaten_kota": "61.03",
      "kode_provinsi": "61"
    },
    {
      "nama_wilayah": "Meliau",
      "kode_wilayah": "61.03.20",
      "level_wilayah": "kecamatan",
      "kode_kabupaten_kota": "61.03",
      "kode_provinsi": "61"
    },
    {
      "nama_wilayah": "Entikong",
      "kode_wilayah": "61.03.21",
      "level_wilayah": "kecamatan",
      "kode_kabupaten_kota": "61.03",
      "kode_provinsi": "61"
    }
  ]
}