{
  "status": "success",
  "total": 17,
  "data": [
    {
      "nama_wilayah": "Modoinding",
      "kode_wilayah": "71.05.01",
      "level_wilayah": "kecamatan",
      "kode_kabupaten_kota": "71.05",
      "kode_provinsi": "71"
    },
    {
      "nama_wilayah": "Tompaso Baru",
      "kode_wilayah": "71.05.02",
      "level_wilayah": "kecamatan",
      "kode_kabupaten_kota": "71.05",
      "kode_provinsi": "71"
    },
    {
      "nama_wilayah": "Ranoyapo",
      "kode_wilayah": "71.05.03",
      "level_wilayah": "kecamatan",
      "kode_kabupaten_kota": "71.05",
      "kode_provinsi": "71"
    },
    {
      "nama_wilayah": "Motoling",
      "kode_wilayah": "71.05.07",
      "level_wilayah": "kecamatan",
      "kode_kabupaten_kota": "71.05",
      "kode_provinsi": "71"
    },
    {
      "nama_wilayah": "Sinonsayang",
      "kode_wilayah": "71.05.08",
      "level_wilayah": "kecamatan",
      "kode_kabupaten_kota": "71.05",
      "kode_provinsi": "71"
    },
    {
      "nama_wilayah": "Tenga",
      "kode_wilayah": "71.05.09",
      "level_wilayah": "kecamatan",
      "kode_kabupaten_kota": "71.05",
      "kode_provinsi": "71"
    },
    {
      "nama_wilayah": "Amurang",
      "kode_wilayah": "71.05.10",
      "level_wilayah": "kecamatan",
      "kode_kabupaten_kota": "71.05",
      "kode_provinsi": "71"
    },
    {
      "nama_wilayah": "Tumpaan",
      "kode_wilayah": "71.05.12",
      "level_wilayah": "kecamatan",
      "kode_kabupaten_kota": "71.05",
      "kode_provinsi": "71"
    },
    {
      "nama_wilayah": "Tareran",
      "kode_wilayah": "71.05.13",
      "level_wilayah": "kecamatan",
      "kode_kabupaten_kota": "71.05",
      "kode_provinsi": "71"
    },
    {
      "nama_wilayah": "Kumelembuai",
      "kode_wilayah": "71.05.15",
      "level_wilayah": "kecamatan",
      "kode_kabupaten_kota": "71.05",
      "kode_provinsi": "71"
    },
    {
      "nama_wilayah": "Maesaan",
      "kode_wilayah": "71.05.16",
      "level_wilayah": "kecamatan",
      "kode_kabupaten_kota": "71.05",
      "kode_provinsi": "71"
    },
    {
      "nama_wilayah": "Amurang Barat",
      "kode_wilayah": "71.05.17",
      "level_wilayah": "kecamatan",
      "kode_kabupaten_kota": "71.05",
      "kode_provinsi": "71"
    },
    {
      "nama_wilayah": "Amurang Timur",
      "kode_wilayah": "71.05.18",
      "level_wilayah": "kecamatan",
      "kode_kabupaten_kota": "71.05",
      "kode_provinsi": "71"
    },
    {
      "nama_wilayah": "Tatapaan",
      "kode_wilayah": "71.05.19",
      "level_wilayah": "kecamatan",
      "kode_kabupaten_kota": "71.05",
      "kode_provinsi": "71"
    },
    {
      "nama_wilayah": "Motoling Barat",
      "kode_wilayah": "71.05.21",
      "level_wilayah": "kecamatan",
      "kode_kabupaten_kota": "71.05",
      "kode_provinsi": "71"
    },
    {
      "nama_wilayah": "Motoling Timur",
      "kode_wilayah": "71.05.22",
      "level_wilayah": "kecamatan",
      "kode_kabupaten_kota": "71.05",
      "kode_provinsi": "71"
    },
    {
      "nama_wilayah": "Suluun Tareran",
      "kode_wilayah": "71.05.23",
      "level_wilayah": "kecamatan",
      "kode_kabupaten_kota": "71.05",
      "kode_provinsi": "71"
    }
  ]
}