{
  "status": "success",
  "total": 16,
  "data": [
    {
      "nama_wilayah": "Rio Pakava",
      "kode_wilayah": "72.03.04",
      "level_wilayah": "kecamatan",
      "kode_kabupaten_kota": "72.03",
      "kode_provinsi": "72"
    },
    {
      "nama_wilayah": "Dampelas",
      "kode_wilayah": "72.03.06",
      "level_wilayah": "kecamatan",
      "kode_kabupaten_kota": "72.03",
      "kode_provinsi": "72"
    },
    {
      "nama_wilayah": "Banawa",
      "kode_wilayah": "72.03.08",
      "level_wilayah": "kecamatan",
      "kode_kabupaten_kota": "72.03",
      "kode_provinsi": "72"
    },
    {
      "nama_wilayah": "Labuan",
      "kode_wilayah": "72.03.09",
      "level_wilayah": "kecamatan",
      "kode_kabupaten_kota": "72.03",
      "kode_provinsi": "72"
    },
    {
      "nama_wilayah": "Sindue",
      "kode_wilayah": "72.03.10",
      "level_wilayah": "kecamatan",
      "kode_kabupaten_kota": "72.03",
      "kode_provinsi": "72"
    },
    {
      "nama_wilayah": "Sirenja",
      "kode_wilayah": "72.03.11",
      "level_wilayah": "kecamatan",
      "kode_kabupaten_kota": "72.03",
      "kode_provinsi": "72"
    },
    {
      "nama_wilayah": "Balaesang",
      "kode_wilayah": "72.03.12",
      "level_wilayah": "kecamatan",
      "kode_kabupaten_kota": "72.03",
      "kode_provinsi": "72"
    },
    {
      "nama_wilayah": "Sojol",
      "kode_wilayah": "72.03.14",
      "level_wilayah": "kecamatan",
      "kode_kabupaten_kota": "72.03",
      "kode_provinsi": "72"
    },
    {
      "nama_wilayah": "Banawa Selatan",
      "kode_wilayah": "72.03.18",
      "level_wilayah": "kecamatan",
      "kode_kabupaten_kota": "72.03",
      "kode_provinsi": "72"
    },
    {
      "nama_wilayah": "Tanantovea",
      "kode_wilayah": "72.03.19",
      "level_wilayah": "kecamatan",
      "kode_kabupaten_kota": "72.03",
      "kode_provinsi": "72"
    },
    {
      "nama_wilayah": "Pinembani",
      "kode_wilayah": "72.03.21",
      "level_wilayah": "kecamatan",
      "kode_kabupaten_kota": "72.03",
      "kode_provinsi": "72"
    },
    {
      "nama_wilayah": "Sindue Tombusabora",
      "kode_wilayah": "72.03.24",
      "level_wilayah": "kecamatan",
      "kode_kabupaten_kota": "72.03",
      "kode_provinsi": "72"
    },
    {
      "nama_wilayah": "Sindue Tobata",
      "kode_wilayah": "72.03.25",
      "level_wilayah": "kecamatan",
      "kode_kabupaten_kota": "72.03",
      "kode_provinsi": "72"
    },
    {
      "nama_wilayah": "Banawa Tengah",
      "kode_wilayah": "72.03.27",
      "level_wilayah": "kecamatan",
      "kode_kabupaten_kota": "72.03",
      "kode_provinsi": "72"
    },
    {
      "nama_wilayah": "Sojol Utara",
      "kode_wilayah": "72.03.30",
      "level_wilayah": "kecamatan",
      "kode_kabupaten_kota": "72.03",
      "kode_provinsi": "72"
    },
    {
      "nama_wilayah": "Balaesang Tanjung",
      "kode_wilayah": "72.03.31",
      "level_wilayah": "kecamatan",
      "kode_kabupaten_kota": "72.03",
      "kode_provinsi": "72"
    }
  ]
}