{
  "status": "success",
  "total": 30,
  "data": [
    {
      "nama_wilayah": "Makbon",
      "kode_wilayah": "96.01.01",
      "level_wilayah": "kecamatan",
      "kode_kabupaten_kota": "96.01",
      "kode_provinsi": "96"
    },
    {
      "nama_wilayah": "Salawati",
      "kode_wilayah": "96.01.03",
      "level_wilayah": "kecamatan",
      "kode_kabupaten_kota": "96.01",
      "kode_provinsi": "96"
    },
    {
      "nama_wilayah": "Seget",
      "kode_wilayah": "96.01.04",
      "level_wilayah": "kecamatan",
      "kode_kabupaten_kota": "96.01",
      "kode_provinsi": "96"
    },
    {
      "nama_wilayah": "Aimas",
      "kode_wilayah": "96.01.05",
      "level_wilayah": "kecamatan",
      "kode_kabupaten_kota": "96.01",
      "kode_provinsi": "96"
    },
    {
      "nama_wilayah": "Klamono",
      "kode_wilayah": "96.01.06",
      "level_wilayah": "kecamatan",
      "kode_kabupaten_kota": "96.01",
      "kode_provinsi": "96"
    },
    {
      "nama_wilayah": "Sayosa",
      "kode_wilayah": "96.01.07",
      "level_wilayah": "kecamatan",
      "kode_kabupaten_kota": "96.01",
      "kode_provinsi": "96"
    },
    {
      "nama_wilayah": "Segun",
      "kode_wilayah": "96.01.08",
      "level_wilayah": "kecamatan",
      "kode_kabupaten_kota": "96.01",
      "kode_provinsi": "96"
    },
    {
      "nama_wilayah": "Mayamuk",
      "kode_wilayah": "96.01.09",
      "level_wilayah": "kecamatan",
      "kode_kabupaten_kota": "96.01",
      "kode_provinsi": "96"
    },
    {
      "nama_wilayah": "Salawati Selatan",
      "kode_wilayah": "96.01.10",
      "level_wilayah": "kecamatan",
      "kode_kabupaten_kota": "96.01",
      "kode_provinsi": "96"
    },
    {
      "nama_wilayah": "Klabot",
      "kode_wilayah": "96.01.11",
      "level_wilayah": "kecamatan",
      "kode_kabupaten_kota": "96.01",
      "kode_provinsi": "96"
    },
    {
      "nama_wilayah": "Klawak",
      "kode_wilayah": "96.01.12",
      "level_wilayah": "kecamatan",
      "kode_kabupaten_kota": "96.01",
      "kode_provinsi": "96"
    },
    {
      "nama_wilayah": "Maudus",
      "kode_wilayah": "96.01.13",
      "level_wilayah": "kecamatan",
      "kode_kabupaten_kota": "96.01",
      "kode_provinsi": "96"
    },
    {
      "nama_wilayah": "Mariat",
      "kode_wilayah": "96.01.14",
      "level_wilayah": "kecamatan",
      "kode_kabupaten_kota": "96.01",
      "kode_provinsi": "96"
    },
    {
      "nama_wilayah": "Klaso",
      "kode_wilayah": "96.01.16",
      "level_wilayah": "kecamatan",
      "kode_kabupaten_kota": "96.01",
      "kode_provinsi": "96"
    },
    {
      "nama_wilayah": "Beraur",
      "kode_wilayah": "96.01.02",
      "level_wilayah": "kecamatan",
      "kode_kabupaten_kota": "96.01",
      "kode_provinsi": "96"
    },
    {
      "nama_wilayah": "Sorong",
      "kode_wilayah": "96.01.18",
      "level_wilayah": "kecamatan",
      "kode_kabupaten_kota": "96.01",
      "kode_provinsi": "96"
    },
    {
      "nama_wilayah": "Bagun",
      "kode_wilayah": "96.01.19",
      "level_wilayah": "kecamatan",
      "kode_kabupaten_kota": "96.01",
      "kode_provinsi": "96"
    },
    {
      "nama_wilayah": "Wemak",
      "kode_wilayah": "96.01.20",
      "level_wilayah": "kecamatan",
      "kode_kabupaten_kota": "96.01",
      "kode_provinsi": "96"
    },
    {
      "nama_wilayah": "Sunook",
      "kode_wilayah": "96.01.21",
      "level_wilayah": "kecamatan",
      "kode_kabupaten_kota": "96.01",
      "kode_provinsi": "96"
    },
    {
      "nama_wilayah": "Buk",
      "kode_wilayah": "96.01.22",
      "level_wilayah": "kecamatan",
      "kode_kabupaten_kota": "96.01",
      "kode_provinsi": "96"
    },
    {
      "nama_wilayah": "Malabotom",
      "kode_wilayah": "96.01.24",
      "level_wilayah": "kecamatan",
      "kode_kabupaten_kota": "96.01",
      "kode_provinsi": "96"
    },
    {
      "nama_wilayah": "Konhir",
      "kode_wilayah": "96.01.25",
      "level_wilayah": "kecamatan",
      "kode_kabupaten_kota": "96.01",
      "kode_provinsi": "96"
    },
    {
      "nama_wilayah": "Klasafet",
      "kode_wilayah": "96.01.26",
      "level_wilayah": "kecamatan",
      "kode_kabupaten_kota": "96.01",
      "kode_provinsi": "96"
    },
    {
      "nama_wilayah": "Hobard",
      "kode_wilayah": "96.01.27",
      "level_wilayah": "kecamatan",
      "kode_kabupaten_kota": "96.01",
      "kode_provinsi": "96"
    },
    {
      "nama_wilayah": "Salawati Tengah",
      "kode_wilayah": "96.01.28",
      "level_wilayah": "kecamatan",
      "kode_kabupaten_kota": "96.01",
      "kode_provinsi": "96"
    },
    {
      "nama_wilayah": "Botain",
      "kode_wilayah": "96.01.29",
      "level_wilayah": "kecamatan",
      "kode_kabupaten_kota": "96.01",
      "kode_provinsi": "96"
    },
    {
      "nama_wilayah": "Sayosa Timur",
      "kode_wilayah": "96.01.30",
      "level_wilayah": "kecamatan",
      "kode_kabupaten_kota": "96.01",
      "kode_provinsi": "96"
    },
    {
      "nama_wilayah": "Klayili",
      "kode_wilayah": "96.01.15",
      "level_wilayah": "kecamatan",
      "kode_kabupaten_kota": "96.01",
      "kode_provinsi": "96"
    },
    {
      "nama_wilayah": "Moisegen",
      "kode_wilayah": "96.01.17",
      "level_wilayah": "kecamatan",
      "kode_kabupaten_kota": "96.01",
      "kode_provinsi": "96"
    },
    {
      "nama_wilayah": "Saengkeduk",
      "kode_wilayah": "96.01.23",
      "level_wilayah": "kecamatan",
      "kode_kabupaten_kota": "96.01",
      "kode_provinsi": "96"
    }
  ]
}