{
  "status": "success",
  "total": 9,
  "data": [
    {
      "nama_wilayah": "Muaro",
      "kode_wilayah": "13.03.04.2001",
      "level_wilayah": "desa_kelurahan",
      "kode_provinsi": "13",
      "kode_kabkota": "13.03",
      "kode_kecamatan": "13.03.04"
    },
    {
      "nama_wilayah": "Kandang Baru",
      "kode_wilayah": "13.03.04.2002",
      "level_wilayah": "desa_kelurahan",
      "kode_provinsi": "13",
      "kode_kabkota": "13.03",
      "kode_kecamatan": "13.03.04"
    },
    {
      "nama_wilayah": "Silokek",
      "kode_wilayah": "13.03.04.2003",
      "level_wilayah": "desa_kelurahan",
      "kode_provinsi": "13",
      "kode_kabkota": "13.03",
      "kode_kecamatan": "13.03.04"
    },
    {
      "nama_wilayah": "Pematang Panjang",
      "kode_wilayah": "13.03.04.2004",
      "level_wilayah": "desa_kelurahan",
      "kode_provinsi": "13",
      "kode_kabkota": "13.03",
      "kode_kecamatan": "13.03.04"
    },
    {
      "nama_wilayah": "Solok Ambah",
      "kode_wilayah": "13.03.04.2005",
      "level_wilayah": "desa_kelurahan",
      "kode_provinsi": "13",
      "kode_kabkota": "13.03",
      "kode_kecamatan": "13.03.04"
    },
    {
      "nama_wilayah": "Paru",
      "kode_wilayah": "13.03.04.2006",
      "level_wilayah": "desa_kelurahan",
      "kode_provinsi": "13",
      "kode_kabkota": "13.03",
      "kode_kecamatan": "13.03.04"
    },
    {
      "nama_wilayah": "Durian Gadang",
      "kode_wilayah": "13.03.04.2007",
      "level_wilayah": "desa_kelurahan",
      "kode_provinsi": "13",
      "kode_kabkota": "13.03",
      "kode_kecamatan": "13.03.04"
    },
    {
      "nama_wilayah": "Aie Angek",
      "kode_wilayah": "13.03.04.2008",
      "level_wilayah": "desa_kelurahan",
      "kode_provinsi": "13",
      "kode_kabkota": "13.03",
      "kode_kecamatan": "13.03.04"
    },
    {
      "nama_wilayah": "Sijunjung",
      "kode_wilayah": "13.03.04.2009",
      "level_wilayah": "desa_kelurahan",
      "kode_provinsi": "13",
      "kode_kabkota": "13.03",
      "kode_kecamatan": "13.03.04"
    }
  ]
}