{
  "status": "success",
  "total": 8,
  "data": [
    {
      "nama_wilayah": "Sidodadi",
      "kode_wilayah": "35.07.29.2001",
      "level_wilayah": "desa_kelurahan",
      "kode_provinsi": "35",
      "kode_kabkota": "35.07",
      "kode_kecamatan": "35.07.29"
    },
    {
      "nama_wilayah": "Gajahrejo",
      "kode_wilayah": "35.07.29.2002",
      "level_wilayah": "desa_kelurahan",
      "kode_provinsi": "35",
      "kode_kabkota": "35.07",
      "kode_kecamatan": "35.07.29"
    },
    {
      "nama_wilayah": "Sindurejo",
      "kode_wilayah": "35.07.29.2003",
      "level_wilayah": "desa_kelurahan",
      "kode_provinsi": "35",
      "kode_kabkota": "35.07",
      "kode_kecamatan": "35.07.29"
    },
    {
      "nama_wilayah": "Gedangan",
      "kode_wilayah": "35.07.29.2004",
      "level_wilayah": "desa_kelurahan",
      "kode_provinsi": "35",
      "kode_kabkota": "35.07",
      "kode_kecamatan": "35.07.29"
    },
    {
      "nama_wilayah": "Segaran",
      "kode_wilayah": "35.07.29.2005",
      "level_wilayah": "desa_kelurahan",
      "kode_provinsi": "35",
      "kode_kabkota": "35.07",
      "kode_kecamatan": "35.07.29"
    },
    {
      "nama_wilayah": "Sumberejo",
      "kode_wilayah": "35.07.29.2006",
      "level_wilayah": "desa_kelurahan",
      "kode_provinsi": "35",
      "kode_kabkota": "35.07",
      "kode_kecamatan": "35.07.29"
    },
    {
      "nama_wilayah": "Tumpakrejo",
      "kode_wilayah": "35.07.29.2007",
      "level_wilayah": "desa_kelurahan",
      "kode_provinsi": "35",
      "kode_kabkota": "35.07",
      "kode_kecamatan": "35.07.29"
    },
    {
      "nama_wilayah": "Girimulyo",
      "kode_wilayah": "35.07.29.2008",
      "level_wilayah": "desa_kelurahan",
      "kode_provinsi": "35",
      "kode_kabkota": "35.07",
      "kode_kecamatan": "35.07.29"
    }
  ]
}