{
  "status": "success",
  "total": 4,
  "data": [
    {
      "nama_wilayah": "Siantan Hulu",
      "kode_wilayah": "61.71.04.1001",
      "level_wilayah": "desa_kelurahan",
      "kode_provinsi": "61",
      "kode_kabkota": "61.71",
      "kode_kecamatan": "61.71.04"
    },
    {
      "nama_wilayah": "Siantan Tengah",
      "kode_wilayah": "61.71.04.1002",
      "level_wilayah": "desa_kelurahan",
      "kode_provinsi": "61",
      "kode_kabkota": "61.71",
      "kode_kecamatan": "61.71.04"
    },
    {
      "nama_wilayah": "Siantan Hilir",
      "kode_wilayah": "61.71.04.1003",
      "level_wilayah": "desa_kelurahan",
      "kode_provinsi": "61",
      "kode_kabkota": "61.71",
      "kode_kecamatan": "61.71.04"
    },
    {
      "nama_wilayah": "Batulayang",
      "kode_wilayah": "61.71.04.1004",
      "level_wilayah": "desa_kelurahan",
      "kode_provinsi": "61",
      "kode_kabkota": "61.71",
      "kode_kecamatan": "61.71.04"
    }
  ]
}