{
  "status": "success",
  "total": 6,
  "data": [
    {
      "nama_wilayah": "Humbia",
      "kode_wilayah": "71.09.10.2001",
      "level_wilayah": "desa_kelurahan",
      "kode_provinsi": "71",
      "kode_kabkota": "71.09",
      "kode_kecamatan": "71.09.10"
    },
    {
      "nama_wilayah": "Kisihang",
      "kode_wilayah": "71.09.10.2002",
      "level_wilayah": "desa_kelurahan",
      "kode_provinsi": "71",
      "kode_kabkota": "71.09",
      "kode_kecamatan": "71.09.10"
    },
    {
      "nama_wilayah": "Bira Kiama",
      "kode_wilayah": "71.09.10.2003",
      "level_wilayah": "desa_kelurahan",
      "kode_provinsi": "71",
      "kode_kabkota": "71.09",
      "kode_kecamatan": "71.09.10"
    },
    {
      "nama_wilayah": "Buha",
      "kode_wilayah": "71.09.10.2004",
      "level_wilayah": "desa_kelurahan",
      "kode_provinsi": "71",
      "kode_kabkota": "71.09",
      "kode_kecamatan": "71.09.10"
    },
    {
      "nama_wilayah": "Batumawira",
      "kode_wilayah": "71.09.10.2005",
      "level_wilayah": "desa_kelurahan",
      "kode_provinsi": "71",
      "kode_kabkota": "71.09",
      "kode_kecamatan": "71.09.10"
    },
    {
      "nama_wilayah": "Birarikei",
      "kode_wilayah": "71.09.10.2006",
      "level_wilayah": "desa_kelurahan",
      "kode_provinsi": "71",
      "kode_kabkota": "71.09",
      "kode_kecamatan": "71.09.10"
    }
  ]
}