{
  "status": "success",
  "total": 9,
  "data": [
    {
      "nama_wilayah": "Toabo",
      "kode_wilayah": "76.02.07.2001",
      "level_wilayah": "desa_kelurahan",
      "kode_provinsi": "76",
      "kode_kabkota": "76.02",
      "kode_kecamatan": "76.02.07"
    },
    {
      "nama_wilayah": "Papalang",
      "kode_wilayah": "76.02.07.2002",
      "level_wilayah": "desa_kelurahan",
      "kode_provinsi": "76",
      "kode_kabkota": "76.02",
      "kode_kecamatan": "76.02.07"
    },
    {
      "nama_wilayah": "Bonda",
      "kode_wilayah": "76.02.07.2003",
      "level_wilayah": "desa_kelurahan",
      "kode_provinsi": "76",
      "kode_kabkota": "76.02",
      "kode_kecamatan": "76.02.07"
    },
    {
      "nama_wilayah": "Topore",
      "kode_wilayah": "76.02.07.2004",
      "level_wilayah": "desa_kelurahan",
      "kode_provinsi": "76",
      "kode_kabkota": "76.02",
      "kode_kecamatan": "76.02.07"
    },
    {
      "nama_wilayah": "Salukayu",
      "kode_wilayah": "76.02.07.2005",
      "level_wilayah": "desa_kelurahan",
      "kode_provinsi": "76",
      "kode_kabkota": "76.02",
      "kode_kecamatan": "76.02.07"
    },
    {
      "nama_wilayah": "Sukadamai",
      "kode_wilayah": "76.02.07.2006",
      "level_wilayah": "desa_kelurahan",
      "kode_provinsi": "76",
      "kode_kabkota": "76.02",
      "kode_kecamatan": "76.02.07"
    },
    {
      "nama_wilayah": "Boda-Boda",
      "kode_wilayah": "76.02.07.2007",
      "level_wilayah": "desa_kelurahan",
      "kode_provinsi": "76",
      "kode_kabkota": "76.02",
      "kode_kecamatan": "76.02.07"
    },
    {
      "nama_wilayah": "Sisango",
      "kode_wilayah": "76.02.07.2008",
      "level_wilayah": "desa_kelurahan",
      "kode_provinsi": "76",
      "kode_kabkota": "76.02",
      "kode_kecamatan": "76.02.07"
    },
    {
      "nama_wilayah": "Batu Ampa",
      "kode_wilayah": "76.02.07.2009",
      "level_wilayah": "desa_kelurahan",
      "kode_provinsi": "76",
      "kode_kabkota": "76.02",
      "kode_kecamatan": "76.02.07"
    }
  ]
}