{
  "status": "success",
  "total": 8,
  "data": [
    {
      "nama_wilayah": "Simboro",
      "kode_wilayah": "76.02.12.1001",
      "level_wilayah": "desa_kelurahan",
      "kode_provinsi": "76",
      "kode_kabkota": "76.02",
      "kode_kecamatan": "76.02.12"
    },
    {
      "nama_wilayah": "Rangas",
      "kode_wilayah": "76.02.12.1002",
      "level_wilayah": "desa_kelurahan",
      "kode_provinsi": "76",
      "kode_kabkota": "76.02",
      "kode_kecamatan": "76.02.12"
    },
    {
      "nama_wilayah": "Botteng",
      "kode_wilayah": "76.02.12.2003",
      "level_wilayah": "desa_kelurahan",
      "kode_provinsi": "76",
      "kode_kabkota": "76.02",
      "kode_kecamatan": "76.02.12"
    },
    {
      "nama_wilayah": "Saletto",
      "kode_wilayah": "76.02.12.2004",
      "level_wilayah": "desa_kelurahan",
      "kode_provinsi": "76",
      "kode_kabkota": "76.02",
      "kode_kecamatan": "76.02.12"
    },
    {
      "nama_wilayah": "Sumare",
      "kode_wilayah": "76.02.12.2005",
      "level_wilayah": "desa_kelurahan",
      "kode_provinsi": "76",
      "kode_kabkota": "76.02",
      "kode_kecamatan": "76.02.12"
    },
    {
      "nama_wilayah": "Botteng Utara",
      "kode_wilayah": "76.02.12.2007",
      "level_wilayah": "desa_kelurahan",
      "kode_provinsi": "76",
      "kode_kabkota": "76.02",
      "kode_kecamatan": "76.02.12"
    },
    {
      "nama_wilayah": "Tapandullu",
      "kode_wilayah": "76.02.12.2008",
      "level_wilayah": "desa_kelurahan",
      "kode_provinsi": "76",
      "kode_kabkota": "76.02",
      "kode_kecamatan": "76.02.12"
    },
    {
      "nama_wilayah": "Pati-di",
      "kode_wilayah": "76.02.12.2009",
      "level_wilayah": "desa_kelurahan",
      "kode_provinsi": "76",
      "kode_kabkota": "76.02",
      "kode_kecamatan": "76.02.12"
    }
  ]
}